pymicroservice/__init__.py
pymicroservice/cli.py
pymicroservice/errors.py
pymicroservice/util.py
pymicroservice/client/__init__.py
pymicroservice/client/remote_service.py
pymicroservice/core/__init__.py
pymicroservice/core/decorators.py
pymicroservice/core/handlers.py
pymicroservice/core/microservice.py
pymicroservice/data/__init__.py
pymicroservice/data/newservice.tmpl
pymicroservice-0.0.3.dist-info/DESCRIPTION.rst
pymicroservice-0.0.3.dist-info/METADATA
pymicroservice-0.0.3.dist-info/RECORD
pymicroservice-0.0.3.dist-info/WHEEL
pymicroservice-0.0.3.dist-info/entry_points.txt
pymicroservice-0.0.3.dist-info/metadata.json
pymicroservice-0.0.3.dist-info/top_level.txt
tests/__init__.py
tests/test_client.py
tests/test_jsonrpc_specs.py
tests/test_pymicroservice.py
tests/test_service_creation.py
