Metadata-Version: 2.0
Name: pymicroservice
Version: 0.0.3
Summary: Build microservices with Python
Home-page: https://github.com/vladcalin/pymicroservice
Author: Vlad Calin
Author-email: vlad.s.calin@gmail.com
License: MIT
Keywords: microservice,cloud,rpc,compute,service
Platform: UNKNOWN
Classifier: Development Status :: 2 - Pre-Alpha
Classifier: License :: OSI Approved :: MIT License
Classifier: Operating System :: OS Independent
Classifier: Programming Language :: Python :: 3 :: Only
Classifier: Topic :: Software Development :: Libraries
Requires-Dist: click
Requires-Dist: tornado
